[
    {
        "type": "tree",
        "location": {
            "x": 32.013771057128906,
            "z": 41.99049186706543
        },
        "rotation": {
            "x": 0.0,
            "y": 0.0,
            "z": 0.0
        },
        "scale": {
            "x": 0.44067642092704773,
            "y": 0.44067636132240295,
            "z": 0.44067633152008057
        },
        "size": {
            "width": 4.271000385284424,
            "height": 4.322941780090332,
            "length": 5.499876499176025
        }
    },
    {
        "type": "tree.001",
        "location": {
            "x": 64.84042739868164,
            "z": 44.39978790283203
        },
        "rotation": {
            "x": 0.0,
            "y": 0.0,
            "z": 0.0
        },
        "scale": {
            "x": 0.646182656288147,
            "y": 0.6461825966835022,
            "z": 0.6461825370788574
        },
        "size": {
            "width": 6.262750625610352,
            "height": 6.33891487121582,
            "length": 8.064703941345215
        }
    },
    {
        "type": "tree.002",
        "location": {
            "x": 110.39117813110352,
            "z": 77.22644424438477
        },
        "rotation": {
            "x": 0.0,
            "y": 0.0,
            "z": 0.0
        },
        "scale": {
            "x": 0.5604437589645386,
            "y": 0.560443639755249,
            "z": 0.5604435801506042
        },
        "size": {
            "width": 5.4317755699157715,
            "height": 5.497833251953125,
            "length": 6.994636058807373
        }
    },
    {
        "type": "tree.003",
        "location": {
            "x": 101.58219146728516,
            "z": 23.77019500732422
        },
        "rotation": {
            "x": 0.0,
            "y": 0.0,
            "z": 0.0
        },
        "scale": {
            "x": 0.8336020708084106,
            "y": 0.8336018919944763,
            "z": 0.8336018919944763
        },
        "size": {
            "width": 8.079203605651855,
            "height": 8.177457809448242,
            "length": 10.40379810333252
        }
    },
    {
        "type": "tree.004",
        "location": {
            "x": 28.324539184570312,
            "z": 87.01420974731445
        },
        "rotation": {
            "x": 0.0,
            "y": 0.0,
            "z": 0.0
        },
        "scale": {
            "x": 0.45831990242004395,
            "y": 0.4583197832107544,
            "z": 0.4583198130130768
        },
        "size": {
            "width": 4.441999912261963,
            "height": 4.496020317077637,
            "length": 5.720076560974121
        }
    },
    {
        "type": "tree.005",
        "location": {
            "x": 109.63827514648438,
            "z": 113.4411735534668
        },
        "rotation": {
            "x": 0.0,
            "y": 0.0,
            "z": 0.0
        },
        "scale": {
            "x": 0.9374454021453857,
            "y": 0.937445342540741,
            "z": 0.9374452233314514
        },
        "size": {
            "width": 9.08564567565918,
            "height": 9.19614028930664,
            "length": 11.69981861114502
        }
    },
    {
        "type": "tree.006",
        "location": {
            "x": 14.040206909179688,
            "z": 80.54684448242188
        },
        "rotation": {
            "x": 0.0,
            "y": 0.0,
            "z": 0.0
        },
        "scale": {
            "x": 0.8105911016464233,
            "y": 0.8105909824371338,
            "z": 0.8105908632278442
        },
        "size": {
            "width": 7.856183052062988,
            "height": 7.951725482940674,
            "length": 10.116607666015625
        }
    },
    {
        "type": "tree.007",
        "location": {
            "x": 10.555984497070312,
            "z": 29.49227523803711
        },
        "rotation": {
            "x": 0.0,
            "y": 0.0,
            "z": 0.0
        },
        "scale": {
            "x": 0.9232544898986816,
            "y": 0.9232544302940369,
            "z": 0.9232543110847473
        },
        "size": {
            "width": 8.948108673095703,
            "height": 9.056930541992188,
            "length": 11.52270793914795
        }
    },
    {
        "type": "tree.008",
        "location": {
            "x": 64.76514434814453,
            "z": 12.100170135498047
        },
        "rotation": {
            "x": 0.0,
            "y": 0.0,
            "z": 0.0
        },
        "scale": {
            "x": 0.4803573787212372,
            "y": 0.48035728931427,
            "z": 0.48035728931427
        },
        "size": {
            "width": 4.655585765838623,
            "height": 4.712203502655029,
            "length": 5.995116233825684
        }
    },
    {
        "type": "tree.009",
        "location": {
            "x": 60.0,
            "z": 60.0
        },
        "rotation": {
            "x": 0.0,
            "y": 0.0,
            "z": 0.0
        },
        "scale": {
            "x": 0.6191640496253967,
            "y": 0.619163990020752,
            "z": 0.619163990020752
        },
        "size": {
            "width": 6.000887870788574,
            "height": 6.073867321014404,
            "length": 7.7274980545043945
        }
    }
]